sphinx_treeview-1.1.1.dist-info/METADATA
sphinx_treeview-1.1.1.dist-info/WHEEL
sphinx_treeview-1.1.1.dist-info/entry_points.txt
sphinx_treeview-1.1.1.dist-info/licenses/LICENSE
sphinx_treeview/__init__.py
sphinx_treeview/assets/dir/file.svg
sphinx_treeview/assets/dir/folder.svg
sphinx_treeview/assets/treeview.css.jinja
sphinx_treeview/assets/treeview.js
sphinx_treeview/decorator.py
sphinx_treeview/directives.py
sphinx_treeview/roles.py
sphinx_treeview/static/.gitignore
sphinx_treeview-1.1.1.dist-info/RECORD
