Metadata-Version: 2.1
Name: sphinx-treeview
Version: 1.1.1
Summary: Add support for tree view to Sphinx.
Author-Email: theogiraudet <theo.giraudet@altearn.xyz>, Aksiome <maxime.calmon@altearn.xyz>
License: MPL-2.0
Classifier: Intended Audience :: Developers
Classifier: Framework :: Sphinx :: Extension
Classifier: License :: OSI Approved :: Mozilla Public License 2.0 (MPL 2.0)
Classifier: Programming Language :: Python :: 3.11
Project-URL: Documentation, https://sphinx-treeview.readthedocs.io
Project-URL: Repository, https://github.com/Altearn/Sphinx-Tree-View
Project-URL: Issues, https://github.com/Altearn/Sphinx-Tree-View/issues
Requires-Python: >=3.11
Requires-Dist: sphinx
Requires-Dist: jinja2
Provides-Extra: docs
Requires-Dist: myst-parser; extra == "docs"
Requires-Dist: furo; extra == "docs"
Requires-Dist: sphinx-inline-tabs; extra == "docs"
